SlyYTAAPI/__init__.py
SlyYTAAPI/__main__.py
SlyYTAAPI/analytics.py
SlyYTAAPI-0.2.0.dist-info/LICENSE
SlyYTAAPI-0.2.0.dist-info/METADATA
SlyYTAAPI-0.2.0.dist-info/WHEEL
SlyYTAAPI-0.2.0.dist-info/top_level.txt
SlyYTAAPI-0.2.0.dist-info/RECORD
