Metadata-Version: 2.1
Name: SlyYTAAPI
Version: 0.2.0
Summary: No-boilerplate, async and typed YouTube Analytics API access.
Author: Dunkyl 🔣🔣
License: MIT License
Project-URL: Homepage, https://docs.dunkyl.net/SlyYTAAPI-Python/
Project-URL: Repository, https://github.com/dunkyl/SlyYTAAPI-Python
Project-URL: Documentation, https://docs.dunkyl.net/SlyYTAAPI-Python/
Project-URL: Bug Tracker, https://github.com/dunkyl/SlyYTAAPI-Python/issues
Classifier: Operating System :: OS Independent
Requires-Python: >=3.10
License-File: LICENSE
Requires-Dist: SlyAPI (>=0.4.3)
Provides-Extra: dev
Requires-Dist: pytest ; extra == 'dev'
Requires-Dist: pytest-asyncio ; extra == 'dev'
Requires-Dist: myst-parser ; extra == 'dev'
Requires-Dist: furo ; extra == 'dev'
Requires-Dist: sphinxcontrib-trio ; extra == 'dev'
Requires-Dist: sphinx-copybutton ; extra == 'dev'
Requires-Dist: sphinxext-opengraph ; extra == 'dev'
